README
ez_setup.py
setup.py
django_sort.egg-info/PKG-INFO
django_sort.egg-info/SOURCES.txt
django_sort.egg-info/dependency_links.txt
django_sort.egg-info/top_level.txt
sorting/__init__.py
sorting/models.py
sorting/tests.py
sorting/views.py