Metadata-Version: 1.0
Name: django-sort
Version: 0.1
Summary: Sort arbitrary querysets in templates.
Home-page: http://github.com/agiliq/django-sorting
Author: Agiliq and friends
Author-email: shabda@agiliq.com
License: UNKNOWN
Platform: UNKNOWN
